alliance_platform/audit/__init__.py
alliance_platform/audit/api.py
alliance_platform/audit/apps.py
alliance_platform/audit/audit.py
alliance_platform/audit/events.py
alliance_platform/audit/middleware.py
alliance_platform/audit/registry.py
alliance_platform/audit/search.py
alliance_platform/audit/settings.py
alliance_platform/audit/templatetags/alliance_platform/__init__.py
alliance_platform/audit/templatetags/alliance_platform/audit.py
alliance_platform/audit/utils.py
alliance_platform/py.typed
alliance_platform_audit-0.0.3.dist-info/METADATA
alliance_platform_audit-0.0.3.dist-info/WHEEL
alliance_platform_audit-0.0.3.dist-info/entry_points.txt
alliance_platform_audit-0.0.3.dist-info/RECORD
