Metadata-Version: 2.1
Name: alliance-platform-audit
Version: 0.0.3
Summary: Alliance Platform Audit
Author-Email: Alliance Software <support@alliancesoftware.com.au>
License: BSD-2-Clause
Requires-Python: >=3.11
Requires-Dist: alliance-platform-core
Requires-Dist: django-pghistory
Requires-Dist: django-pgtrigger
Requires-Dist: Django>=4.2.11
Requires-Dist: django-allianceutils>=4.0
